Metadata-Version: 2.1
Name: sphinxcontrib.kana-text
Version: 0.32.0
Summary: KanaText class extends the functionality of Text class, for someone who use index/glossary directives.
Home-page: https://qiita.com/tags/sphinxcotrib.kana_text
Author: @koKekkoh
Maintainer: KaKkouo
License: BSD 2-Clause License
Download-URL: https://pypi.org/project/sphinxcontrib.kana-text/
Project-URL: Knowledge, https://qiita.com/tags/sphinxcotrib.kana_text
Project-URL: Code, https://github.com/KaKkouo/kana_text
Project-URL: Issue tracker, https://github.com/KaKkouo/kana_text/issues
Keywords: sphinx,sphinxcontrib,japanese,ja,kana_text,glossary,index,kana
Platform: any
Classifier: Development Status :: 4 - Beta
Classifier: Framework :: Sphinx :: Extension
Classifier: Intended Audience :: Developers
Classifier: Intended Audience :: Education
Classifier: License :: OSI Approved :: BSD License
Classifier: Natural Language :: Japanese
Classifier: Operating System :: OS Independent
Classifier: Programming Language :: Python :: 3
Classifier: Programming Language :: Python :: 3 :: Only
Classifier: Programming Language :: Python :: 3.6
Classifier: Programming Language :: Python :: 3.7
Classifier: Programming Language :: Python :: 3.8
Classifier: Topic :: Documentation :: Sphinx
Classifier: Topic :: Utilities
License-File: LICENSE
